[
	{
		"name": "John Dial" ,
		"account": "6021-10331",
		"country": "India",
		"date_of_join": "21 Feb 2021",
		"email": "abc@gmail.com",
		"postal": "P.O. Box 916",
		"phone": "9112345678",
		"brand": "My Brand"
	},
	{
		"name": "Johnson Leverage",
		"account": "16021-1033",
		"country": "Ireland",
		"date_of_join": "22 Feb 2021",
		"email": "abc2@gmail.com",
		"postal": "P.O. Box 91622.",
		"phone": "9012345678",
		"brand": "My Brand1"
	},
	{
		"name": "Jacob Martin",
		"account": "6021-10331",
		"country": "India",
		"date_of_join": "21 Feb 2021",
		"email": "abc@gmail.com",
		"postal": "P.O. Box 916",
		"phone": "9112345678",
		"brand": "My Brand"
	},
	{
		"name": "Ryan Roland",
		"account": "16021-1033",
		"country": "Ireland",
		"date_of_join": "22 Feb 2021",
		"email": "abc2@gmail.com",
		"postal": "P.O. Box 91622.",
		"phone": "9012345678",
		"brand": "My Brand1"
	},
	{
		"name": "Sachin Tendulkar",
		"account": "6021-10331",
		"country": "India",
		"date_of_join": "21 Feb 2021",
		"email": "abc@gmail.com",
		"postal": "P.O. Box 916",
		"phone": "9112345678",
		"brand": "My Brand"
	},
	{
		"name": "Dravid Rahul",
		"account": "16021-1033",
		"country": "Ireland",
		"date_of_join": "22 Feb 2021",
		"email": "abc2@gmail.com",
		"postal": "P.O. Box 91622.",
		"phone": "9012345678",
		"brand": "My Brand1"
	},
	{
		"name": "George Linde",
		"account": "6021-10331",
		"country": "India",
		"date_of_join": "21 Feb 2021",
		"email": "abc@gmail.com",
		"postal": "P.O. Box 916",
		"phone": "9112345678",
		"brand": "My Brand"
	},
	{
		"name": "Kevin Obreyan",
		"account": "16021-1033",
		"country": "Ireland",
		"date_of_join": "22 Feb 2021",
		"email": "abc2@gmail.com",
		"postal": "P.O. Box 91622.",
		"phone": "9012345678",
		"brand": "My Brand1"
	},
	{
		"name": "Johnson Charless",
		"account": "16021-1033",
		"country": "Ireland",
		"date_of_join": "22 Feb 2021",
		"email": "abc2@gmail.com",
		"postal": "P.O. Box 91622.",
		"phone": "9012345678",
		"brand": "My Brand1"
	},
	{
		"name": "Jacob Ridley",
		"account": "6021-10331",
		"country": "India",
		"date_of_join": "21 Feb 2021",
		"email": "abc@gmail.com",
		"postal": "P.O. Box 916",
		"phone": "9112345678",
		"brand": "My Brand"
	},
	{
		"name": "Ryan Livingstone",
		"account": "16021-1033",
		"country": "Ireland",
		"date_of_join": "22 Feb 2021",
		"email": "abc2@gmail.com",
		"postal": "P.O. Box 91622.",
		"phone": "9012345678",
		"brand": "My Brand1"
	},
	{
		"name": "Sachin Yuvraj",
		"account": "6021-10331",
		"country": "India",
		"date_of_join": "21 Feb 2021",
		"email": "abc@gmail.com",
		"postal": "P.O. Box 916",
		"phone": "9112345678",
		"brand": "My Brand"
	},
	{
		"name": "Dravid Marati",
		"account": "16021-1033",
		"country": "Ireland",
		"date_of_join": "22 Feb 2021",
		"email": "abc2@gmail.com",
		"postal": "P.O. Box 91622.",
		"phone": "9012345678",
		"brand": "My Brand1"
	},
	{
		"name": "George McMohan",
		"account": "6021-10331",
		"country": "India",
		"date_of_join": "21 Feb 2021",
		"email": "abc@gmail.com",
		"postal": "P.O. Box 916",
		"phone": "9112345678",
		"brand": "My Brand"
	},
	{
		"name": "Legend Lara",
		"account": "16021-1033",
		"country": "Ireland",
		"date_of_join": "22 Feb 2021",
		"email": "abc2@gmail.com",
		"postal": "P.O. Box 91622.",
		"phone": "9012345678",
		"brand": "My Brand1"
	}
]
	